behavioural_benchmark/__init__.py
behavioural_benchmark/indicators.py
behavioural_benchmark/mean_indicators.py
behavioural_benchmark/network_indicators.py
behavioural_benchmark/regression_indicators.py
behavioural_benchmark/stn.py
behavioural_benchmark/tst/test.py
behavioural_benchmark/tutorials/comparison_guide_utils.py
behaviouralbenchmark-1.0.0.dist-info/licenses/LICENSE
behaviouralbenchmark-1.0.0.dist-info/METADATA
behaviouralbenchmark-1.0.0.dist-info/WHEEL
behaviouralbenchmark-1.0.0.dist-info/top_level.txt
behaviouralbenchmark-1.0.0.dist-info/RECORD
