Metadata-Version: 2.4
Name: behaviouralbenchmark
Version: 1.0.0
Summary: Python implementation of several indicators of metaheuristic search behaviour.
Author-email: Lauren Hayward <haywardlau@gmail.com>
License:                     GNU GENERAL PUBLIC LICENSE
Project-URL: Homepage, https://github.com/runrunLauren/behavioural_benchmarking
Project-URL: Bug Tracker, https://github.com/runrunLauren/behavioural_benchmarking/issues
Classifier: Programming Language :: Python :: 3
Classifier: License :: OSI Approved :: GNU General Public License v3 (GPLv3)
Classifier: Operating System :: OS Independent
Requires-Python: >=3.7
License-File: LICENSE
Requires-Dist: numpy
Requires-Dist: pwlf
Requires-Dist: pandas
Requires-Dist: jupyter
Requires-Dist: igraph
Requires-Dist: scikit-learn
Requires-Dist: matplotlib
Requires-Dist: seaborn
Requires-Dist: scipy
Dynamic: license-file
